face_api
