Metadata-Version: 2.1
Name: face-api
Version: 0.2.6
Summary: Package for Face API
Home-page: http://www.ai.game.tw
Author: BIG CHENG
Author-email: big_cheng.asus@gmail.com
License: UNKNOWN
Platform: UNKNOWN
Classifier: Programming Language :: Python :: 3
Classifier: License :: OSI Approved :: MIT License
Classifier: Operating System :: OS Independent
